{"nodes": [{"id": "compile_smoke_native_compile_contract", "label": "Generated Wrapper Native Compile Contract", "file_type": "code", "source_file": "tests/compile_smoke.rs", "source_location": null, "source_url": null, "captured_at": null, "author": null, "contributor": null}, {"id": "compile_smoke_model_borrow_semantics", "label": "Model Borrow And Ownership Compile Semantics", "file_type": "code", "source_file": "tests/compile_smoke.rs", "source_location": null, "source_url": null, "captured_at": null, "author": null, "contributor": null}], "edges": [{"source": "compile_smoke_native_compile_contract", "target": "parser_parse", "relation": "calls", "confidence": "EXTRACTED", "confidence_score": 1.0, "source_file": "tests/compile_smoke.rs", "source_location": null, "weight": 1.0}, {"source": "compile_smoke_native_compile_contract", "target": "compiler_collect_clang_args", "relation": "conceptually_related_to", "confidence": "INFERRED", "confidence_score": 0.7, "source_file": "tests/compile_smoke.rs", "source_location": null, "weight": 1.0}, {"source": "compile_smoke_model_borrow_semantics", "target": "generator_model_handle_semantics", "relation": "semantically_similar_to", "confidence": "INFERRED", "confidence_score": 0.9, "source_file": "tests/compile_smoke.rs", "source_location": null, "weight": 1.0}], "hyperedges": [{"id": "generated_output_verification_suite", "label": "Generated Output Verification Suite", "nodes": ["compile_smoke_native_compile_contract", "examples_generated_output_checked_in_examples_contract", "facade_generate_facade_wrapper_contract", "generator_renderer_contracts", "model_record_fixture_datarecord_contract", "multi_header_generate_multi_header_contract"], "relation": "form", "confidence": "INFERRED", "confidence_score": 0.85, "source_file": "tests/compile_smoke.rs"}]}